libssentencepiece_core.so
_ssentencepiece.cpython-39-x86_64-linux-gnu.so
simple_sentencepiece-0.10.dist-info/METADATA
simple_sentencepiece-0.10.dist-info/WHEEL
simple_sentencepiece-0.10.dist-info/top_level.txt
simple_sentencepiece-0.10.dist-info/RECORD
simple_sentencepiece-0.10.dist-info/entry_points.txt
simple_sentencepiece-0.10.dist-info/licenses/LICENSE
ssentencepiece/ssentencepiece.py
ssentencepiece/cli.py
ssentencepiece/__init__.py
ssentencepiece/resources/librispeech-5000.vocab
ssentencepiece/resources/zh-en-5776.vocab
ssentencepiece/resources/zh-en-8776.vocab
ssentencepiece/resources/zh-en-3876.vocab
ssentencepiece/resources/zh-en-8481.vocab
ssentencepiece/resources/gigaspeech-2000.vocab
ssentencepiece/resources/zh-en-10381.vocab
ssentencepiece/resources/librispeech-500.vocab
ssentencepiece/resources/chn_jpn_yue_eng_ko_spectok.bpe.vocab
ssentencepiece/resources/zh-en-yue-11661.vocab
ssentencepiece/resources/gigaspeech-500.vocab
ssentencepiece/resources/alphabet-33.vocab
ssentencepiece/resources/zh-en-yue-9761.vocab
ssentencepiece/resources/gigaspeech-5000.vocab
ssentencepiece/resources/alphabet-58.vocab
ssentencepiece/resources/zh-en-6876.vocab
