Metadata-Version: 2.1
Name: simple-sentencepiece
Version: 0.10
Summary: A simple sentencepiece encoder and decoder without any dependency.
Author-email: Next-gen Kaldi development team <wkang@pku.edu.cn>
Project-URL: Homepage, https://github.com/pkufool/simple-sentencepiece
Project-URL: Bug Tracker, https://github.com/pkufool/simple-sentencepiece/issues
Classifier: Programming Language :: Python :: 3
Classifier: License :: OSI Approved :: Apache Software License
Classifier: Operating System :: OS Independent
Requires-Python: >=3.8
License-File: LICENSE
Requires-Dist: click
Requires-Dist: importlib-resources
Requires-Dist: sentencepiece
